{"stats":{"minecraft:used":{"minecraft:leather_leggings":1,"minecraft:leather_helmet":1,"minecraft:leather_chestplate":1,"minecraft:note_block":1,"minecraft:leather_boots":1},"minecraft:dropped":{"minecraft:light":1},"minecraft:custom":{"minecraft:jump":1,"minecraft:time_since_rest":47820,"minecraft:crouch_one_cm":59,"minecraft:sprint_one_cm":97,"minecraft:play_time":47820,"minecraft:time_since_death":47820,"minecraft:walk_one_cm":986,"minecraft:sneak_time":40,"minecraft:total_world_time":47820,"minecraft:drop":1,"minecraft:tune_noteblock":33,"minecraft:fly_one_cm":3737}},"DataVersion":4189}